dnn_cool/__init__.py
dnn_cool/activations.py
dnn_cool/catalyst_utils.py
dnn_cool/converters.py
dnn_cool/datasets.py
dnn_cool/decoders.py
dnn_cool/dsl.py
dnn_cool/evaluation.py
dnn_cool/filter.py
dnn_cool/help.py
dnn_cool/losses.py
dnn_cool/metrics.py
dnn_cool/missing_values.py
dnn_cool/modules.py
dnn_cool/nlp.py
dnn_cool/rf.py
dnn_cool/runner.py
dnn_cool/synthetic_dataset.py
dnn_cool/task_converters.py
dnn_cool/tasks.py
dnn_cool/treelib.py
dnn_cool/tuners.py
dnn_cool/uncertainty.py
dnn_cool/utils.py
dnn_cool/value_converters.py
dnn_cool/verbosity.py
dnn_cool/visitors.py
dnn_cool/collators/__init__.py
dnn_cool/collators/base.py
dnn_cool/converters/__init__.py
dnn_cool/converters/base.py
dnn_cool/converters/full.py
dnn_cool/converters/task/__init__.py
dnn_cool/converters/task/base.py
dnn_cool/converters/values/__init__.py
dnn_cool/converters/values/base.py
dnn_cool/cv/__init__.py
dnn_cool/cv/imagenet.py
dnn_cool/decoders/__init__.py
dnn_cool/decoders/base.py
dnn_cool/decoders/binary.py
dnn_cool/decoders/bounded_regression.py
dnn_cool/decoders/classification.py
dnn_cool/decoders/multilabel_classification.py
dnn_cool/external/__init__.py
dnn_cool/external/autograd.py
dnn_cool/external/torch.py
dnn_cool/losses/__init__.py
dnn_cool/losses/base.py
dnn_cool/losses/torch.py
dnn_cool/memmap/__init__.py
dnn_cool/memmap/base.py
dnn_cool/memmap/string.py
dnn_cool/modules/__init__.py
dnn_cool/modules/base.py
dnn_cool/modules/torch.py
dnn_cool/split/__init__.py
dnn_cool/tasks/__init__.py
dnn_cool/tasks/base.py
dnn_cool/tasks/binary.py
dnn_cool/tasks/bounded_regression.py
dnn_cool/tasks/classification.py
dnn_cool/tasks/multilabel_classification.py
dnn_cool/tasks/task_flow.py
dnn_cool/tasks/development/__init__.py
dnn_cool/tasks/development/base.py
dnn_cool/tasks/development/binary.py
dnn_cool/tasks/development/bounded_regression.py
dnn_cool/tasks/development/classification.py
dnn_cool/tasks/development/multilabel_classification.py
dnn_cool/tasks/development/task_flow.py
dnn_cool-0.3.5.dist-info/LICENSE
dnn_cool-0.3.5.dist-info/METADATA
dnn_cool-0.3.5.dist-info/WHEEL
dnn_cool-0.3.5.dist-info/top_level.txt
dnn_cool-0.3.5.dist-info/RECORD
