Metadata-Version: 2.1
Name: dnn-cool
Version: 0.3.5
Summary: DNN.Cool: Multi-task learning for Deep Neural Networks (DNN).
Home-page: https://github.com/hristo-vrigazov/dnn.cool
Author: Hristo Vrigazov
Author-email: hvrigazov@gmail.com
License: MIT
Platform: UNKNOWN
Classifier: License :: OSI Approved :: MIT License
Classifier: Programming Language :: Python :: 3
Classifier: Programming Language :: Python :: 3.8
Classifier: Operating System :: OS Independent
Requires-Dist: torch
Requires-Dist: pandas
Requires-Dist: numpy
Requires-Dist: tqdm
Requires-Dist: treelib
Requires-Dist: joblib
Provides-Extra: catalyst
Requires-Dist: catalyst (==20.12) ; extra == 'catalyst'
Requires-Dist: scikit-learn ; extra == 'catalyst'
Requires-Dist: matplotlib ; extra == 'catalyst'
Provides-Extra: interpretability
Requires-Dist: captum ; extra == 'interpretability'
Provides-Extra: nlp
Requires-Dist: transformers ; extra == 'nlp'
